README.rst
setup.py
cmph/__init__.py
cmph/_adapters.py
cmph/_utils.py
cmph/bdz.c
cmph/bdz.h
cmph/bdz_ph.c
cmph/bdz_ph.h
cmph/bdz_structs.h
cmph/bdz_structs_ph.h
cmph/bitbool.h
cmph/bmz.c
cmph/bmz.h
cmph/bmz8.c
cmph/bmz8.h
cmph/bmz8_structs.h
cmph/bmz_structs.h
cmph/brz.c
cmph/brz.h
cmph/brz_structs.h
cmph/buffer_entry.c
cmph/buffer_entry.h
cmph/buffer_manager.c
cmph/buffer_manager.h
cmph/chd.c
cmph/chd.h
cmph/chd_ph.c
cmph/chd_ph.h
cmph/chd_structs.h
cmph/chd_structs_ph.h
cmph/chm.c
cmph/chm.h
cmph/chm_structs.h
cmph/cmph.c
cmph/cmph.h
cmph/cmph_benchmark.c
cmph/cmph_benchmark.h
cmph/cmph_structs.c
cmph/cmph_structs.h
cmph/cmph_time.h
cmph/cmph_types.h
cmph/compressed_rank.c
cmph/compressed_rank.h
cmph/compressed_seq.c
cmph/compressed_seq.h
cmph/debug.h
cmph/fch.c
cmph/fch.h
cmph/fch_buckets.c
cmph/fch_buckets.h
cmph/fch_structs.h
cmph/graph.c
cmph/graph.h
cmph/hash.c
cmph/hash.h
cmph/hash_state.h
cmph/jenkins_hash.c
cmph/jenkins_hash.h
cmph/linear_string_map.c
cmph/linear_string_map.h
cmph/logging.c
cmph/logging.h
cmph/miller_rabin.c
cmph/miller_rabin.h
cmph/pyadapter.c
cmph/pyadapter.h
cmph/pylogging.c
cmph/pylogging.h
cmph/select.c
cmph/select.h
cmph/select_lookup_tables.h
cmph/vqueue.c
cmph/vqueue.h
cmph/vstack.c
cmph/vstack.h
cmph/__pycache__/_cffi__x1c73dad3xd2ac377.c
cmph/__pycache__/_cffi__x74a555d1xd2ac377.c
cmph/__pycache__/_cffi__xd5b17556xa88ce482.c
cmph/__pycache__/_cffi__xd90ed4d3xa88ce482.c
cmph_cffi.egg-info/PKG-INFO
cmph_cffi.egg-info/SOURCES.txt
cmph_cffi.egg-info/dependency_links.txt
cmph_cffi.egg-info/not-zip-safe
cmph_cffi.egg-info/requires.txt
cmph_cffi.egg-info/top_level.txt