Metadata-Version: 1.1
Name: cmph-cffi
Version: 0.3.0
Summary: CFFI enabled bindings to the CMPH library forcreating and using minimal perfect hashes
Home-page: http://github.com/URXtech/cmph-cffi/
Author: Greg Bowyer & Venkatesh Sharma
Author-email: gbowyer@fastmail.co.uk & venkatesh@urx.com
License: LGPL-2.1 & MPL-1.1
Keywords: cmph,mph
Platform: UNKNOWN
Classifier: Development Status :: 5 - Production/Stable
Classifier: License :: OSI Approved :: GNU Lesser General Public License v2 or later (LGPLv2+)
Classifier: License :: OSI Approved :: Mozilla Public License 1.1 (MPL 1.1)
Classifier: Intended Audience :: Developers
Classifier: Programming Language :: C
Classifier: Programming Language :: Python
Classifier: Programming Language :: Python :: 2
Classifier: Programming Language :: Python :: 2.7
Classifier: Programming Language :: Python :: Implementation :: CPython
Classifier: Programming Language :: Python :: Implementation :: PyPy
